demo/__init__.py
demo/settings.py
demo/urls.py
demo/wsgi.py
demo/home/__init__.py
demo/home/models.py
demo/home/migrations/0001_initial.py
demo/home/migrations/0002_customimage_dominant_color.py
demo/home/migrations/__init__.py
kontrasto/__init__.py
kontrasto/__main__.py
kontrasto/cli.py
kontrasto/contrast.py
kontrasto/convert.py
kontrasto/dominantcolors.py
kontrasto/lookup_table.py
kontrasto/py.typed
kontrasto/signal_handlers.py
kontrasto/wcag_2.py
kontrasto/wcag_3.py
kontrasto/wcag_3_test.py
kontrasto/willow_operations.py
kontrasto/templatetags/__init__.py
kontrasto/templatetags/kontrasto_tags.py
kontrasto-0.1.0.dist-info/LICENSE
kontrasto-0.1.0.dist-info/METADATA
kontrasto-0.1.0.dist-info/WHEEL
kontrasto-0.1.0.dist-info/entry_points.txt
kontrasto-0.1.0.dist-info/top_level.txt
kontrasto-0.1.0.dist-info/RECORD
