Metadata-Version: 2.1
Name: kontrasto
Version: 0.1.0
Summary: 🎨 Automated color contrast for text over images
Home-page: https://github.com/thibaudcolas/kontrasto
Author: Thibaud Colas
Author-email: thibaudcolas@gmail.com
License: MIT
Keywords: kontrasto,color,colour,contrast,dominant colors,accessibility,a11y,wcag,apca
Platform: UNKNOWN
Classifier: Development Status :: 3 - Alpha
Classifier: Intended Audience :: Developers
Classifier: License :: OSI Approved :: MIT License
Classifier: Typing :: Typed
Classifier: Programming Language :: Python :: 3
Classifier: Programming Language :: Python :: 3 :: Only
Classifier: Programming Language :: Python :: 3.6
Classifier: Programming Language :: Python :: 3.7
Classifier: Programming Language :: Python :: 3.8
Classifier: Programming Language :: Python :: 3.9
Classifier: Programming Language :: Python :: 3.10
Requires-Python: >=3.6
Requires-Dist: numpy
Requires-Dist: Pillow
